jobsubmitG16
