Metadata-Version: 2.1
Name: jobsubmitG16
Version: 1.0.1
Summary: A python program for bulk job submission in NDSU CCAST Prime HPC cluster
Author: Mohammed A. Jabed,
Author-email: jabed.abu@gmail.com
Keywords: gaussian,compchem,ccast,ndsu
Requires-Python: >=3.0
License-File: LICENSE.txt
Requires-Dist: argparse
